{
  "task_groups": [
    { "id": "POS", "order": 1, "code": "POS", 
      "color": {
        "name": "slate", "bg": "#e2e8f0", "text": "#1e293b", "border": "#94a3b8", "hover": "#cbd5e1",
        "tailwind_bg": "bg-slate-200", "tailwind_text": "text-slate-800", "tailwind_border": "border-slate-500"
      },
      "tasks": [
        { "order": "1", "name": "Mở POS", "typeTask": "Fixed", "frequency": "Daily", "frequencyNumber": 1, "reUnit": 10, "manual_number": "POS-001", "manual_link": "", "note": "Tính theo số lượng POS", "concurrentPerformers": 1, "allowedPositions": ["POS", "Leader"],
          "timeWindows": [ { "startTime": "05:40", "endTime": "05:50" } ] },
        { "order": "2", "name": "EOD POS", "typeTask": "Fixed", "frequency": "Daily", "frequencyNumber": 1, "reUnit": 15, "manual_number": "POS-002", "manual_link": "", "note": "Tính theo số lượng POS", "concurrentPerformers": 1, "allowedPositions": ["POS", "Leader"],
          "timeWindows": [ { "startTime": "22:20", "endTime": "22:30" } ] },
        { "order": "3", "name": "Chuẩn bị POS", "typeTask": "Fixed", "frequency": "Daily", "frequencyNumber": 1, "reUnit": 5, "manual_number": "POS-003", "manual_link": "", "note": "Tính theo số lượng POS", "concurrentPerformers": 1, "allowedPositions": ["POS", "Leader"],
          "timeWindows": [ { "startTime": "05:55", "endTime": "06:00" } ] },
        { "order": "4", "name": "Đổi tiền lẻ", "typeTask": "CTM", "frequency": "Daily", "frequencyNumber": 2, "reUnit": 5, "manual_number": "POS-004", "manual_link": "", "note": "Tính theo số lượng POS", "concurrentPerformers": 1, "allowedPositions": ["POS", "Leader"],
          "timeWindows": [ { "startTime": "10:00", "endTime": "10:10" }, { "startTime": "16:00", "endTime": "16:10" }, { "startTime": "19:00", "endTime": "19:10" } ] },
        { "order": "5", "name": "Thế cơm POS Staff", "typeTask": "CTM", "frequency": "Daily", "frequencyNumber": 1, "reUnit": 30, "manual_number": "POS-005", "manual_link": "", "note": "Tính theo số lượng POS", "concurrentPerformers": 1, "allowedPositions": ["POS", "Leader"],
          "timeWindows": [ { "startTime": "10:00", "endTime": "10:10" }, { "startTime": "11:00", "endTime": "11:10" }, { "startTime": "16:00", "endTime": "16:10" }, { "startTime": "17:00", "endTime": "17:10" } ] },
        { "order": "6", "name": "Thế cơm POS -Leader", "typeTask": "Fixed", "frequency": "Daily", "frequencyNumber": 1, "reUnit": 30, "manual_number": "POS-005", "manual_link": "", "note": "Tính theo số lượng POS", "concurrentPerformers": 1, "allowedPositions": ["POS", "Leader"],
          "timeWindows": [ { "startTime": "10:00", "endTime": "10:10" }, { "startTime": "11:00", "endTime": "11:10" }, { "startTime": "16:00", "endTime": "16:10" }, { "startTime": "17:00", "endTime": "17:10" } ] },
        { "order": "7", "name": "Hỗ trợ POS", "typeTask": "CTM", "frequency": "Daily", "frequencyNumber": 1, "reUnit": 60, "manual_number": "POS-006", "manual_link": "", "note": "Tính theo số lượng POS", "concurrentPerformers": 2, "allowedPositions": ["POS", "Leader", "Ngành hàng", "Aeon Cafe"],
          "timeWindows": [ { "startTime": "10:00", "endTime": "11:00" }, { "startTime": "17:00", "endTime": "18:00" } ] },
        { "order": "8", "name": "Kết ca", "typeTask": "Fixed", "frequency": "Daily", "frequencyNumber": 1, "reUnit": 15, "manual_number": "POS-007", "manual_link": "", "note": "Tính theo số lượng POS", "concurrentPerformers": 1, "allowedPositions": ["POS", "Leader"],
          "timeWindows": [ { "startTime": "22:00", "endTime": "22:20" } ] },
        { "order": "9", "name": "Giao ca", "typeTask": "Fixed", "frequency": "Daily", "frequencyNumber": 1, "reUnit": 10, "manual_number": "POS-008", "manual_link": "", "note": "Tính theo số lượng POS", "concurrentPerformers": 1, "allowedPositions": ["POS", "Leader"],
          "timeWindows": [ { "startTime": "13:30", "endTime": "13:45" } ] },
        { "order": "10", "name": "POS 1", "typeTask": "CTM", "frequency": "Daily", "frequencyNumber": 1, "reUnit": 1, "manual_number": "POS-009", "manual_link": "", "note": "Tính theo số lượng khách hàng", "concurrentPerformers": 1, "allowedPositions": ["POS", "Leader"],
          "timeWindows": [ { "startTime": "06:00", "endTime": "22:00" } ] },
        { "order": "11", "name": "POS 2", "typeTask": "CTM", "frequency": "Daily", "frequencyNumber": 1, "reUnit": 1, "manual_number": "POS-010", "manual_link": "", "note": "Tính theo số lượng khách hàng", "concurrentPerformers": 1, "allowedPositions": ["POS", "Leader"],
          "timeWindows": [ { "startTime": "06:00", "endTime": "22:00" } ] },
        { "order": "12", "name": "POS 3", "typeTask": "CTM", "frequency": "Daily", "frequencyNumber": 1, "reUnit": 1, "manual_number": "POS-011", "manual_link": "", "note": "Tính theo số lượng khách hàng", "concurrentPerformers": 1, "allowedPositions": ["POS", "Leader"],
          "timeWindows": [ { "startTime": "06:00", "endTime": "22:00" } ] },
        { "order": "13", "name": "Thế cơm Leader", "typeTask": "Fixed", "frequency": "Daily", "frequencyNumber": 1, "reUnit": 30, "manual_number": "POS-012", "manual_link": "", "note": "Tính theo số lượng POS", "concurrentPerformers": 1, "allowedPositions": ["POS", "Leader"],
          "timeWindows": [ { "startTime": "10:00", "endTime": "10:10" }, { "startTime": "11:00", "endTime": "11:10" }, { "startTime": "16:00", "endTime": "16:10" }, { "startTime": "17:00", "endTime": "17:10" } ] }
      ]},
    { "id": "PERI", "order": 2, "code": "PERI", 
      "color": {
        "name": "green", "bg": "#bbf7d0", "text": "#166534", "border": "#4ade80", "hover": "#86efac",
        "tailwind_bg": "bg-green-200", "tailwind_text": "text-green-800", "tailwind_border": "border-green-500"
      },
      "tasks": [
        { "order": "1", "name": "Lên hàng thịt cá", "typeTask": "Product", "frequency": "Daily", "frequencyNumber": 2, "reUnit": 1.5, "manual_number": "PER-001", "manual_link": "", "note": "Tính theo khối lượng rau củ (kg)", "concurrentPerformers": 2, "allowedPositions": ["Ngành hàng", "Leader"],
          "timeWindows": [ { "startTime": "06:00", "endTime": "11:00" } ] },
        { "order": "2", "name": "Lên hàng trái cây rau củ", "typeTask": "Product", "frequency": "Daily", "frequencyNumber": 3, "reUnit": 1.5, "manual_number": "PER-002", "manual_link": "", "note": "Tính theo khối lượng rau củ (kg)", "concurrentPerformers": 2, "allowedPositions": ["Ngành hàng", "Leader"],
          "timeWindows": [ { "startTime": "06:00", "endTime": "11:00" } ] },
        { "order": "3", "name": "Lên hàng tươi sống", "typeTask": "Product", "frequency": "Daily", "frequencyNumber": 1, "reUnit": 30, "manual_number": "PER-003", "manual_link": "", "note": "Tính theo lần", "concurrentPerformers": 0, "allowedPositions": ["Ngành hàng", "Leader"],
          "timeWindows": [ { "startTime": "06:00", "endTime": "11:00" } ] },
        { "order": "4", "name": "Repack", "typeTask": "Product", "frequency": "Daily", "frequencyNumber": 1, "reUnit": 1.5, "manual_number": "PER-004", "manual_link": "", "note": "Tính theo khối lượng rau củ (kg)", "concurrentPerformers": 2, "allowedPositions": ["Ngành hàng", "Leader"],
          "timeWindows": [ { "startTime": "15:30", "endTime": "16:00" } ] },
        { "order": "5", "name": "Cắt gọt / Cut Fruit", "typeTask": "Product", "frequency": "Daily", "frequencyNumber": 1, "reUnit": 2, "manual_number": "PER-005", "manual_link": "", "note": "Tính theo khối lượng rau củ (kg)", "concurrentPerformers": 2, "allowedPositions": ["Ngành hàng", "Leader"],
          "timeWindows": [ { "startTime": "10:00", "endTime": "10:30" } ] },
        { "order": "6", "name": "Hủy hàng- Staff", "typeTask": "Product", "frequency": "Daily", "frequencyNumber": 1, "reUnit": 20, "manual_number": "PER-006", "manual_link": "", "note": "Tính theo lần", "concurrentPerformers": 1, "allowedPositions": ["Ngành hàng", "Leader"],
          "timeWindows": [ { "startTime": "13:30", "endTime": "13:45" }, { "startTime": "22:00", "endTime": "22:15" } ] },
        { "order": "7", "name": "Kiểm tra HSD Tươi Sống Staff", "typeTask": "Product", "frequency": "Daily", "frequencyNumber": 2, "reUnit": 15, "manual_number": "PER-007", "manual_link": "", "note": "Tính theo lần", "concurrentPerformers": 2, "allowedPositions": ["Ngành hàng", "Leader"],
          "timeWindows": [ { "startTime": "21:30", "endTime": "22:00" } ] },
        { "order": "8", "name": "Đặt hàng Tươi Sống / Order", "typeTask": "Product", "frequency": "Daily", "frequencyNumber": 1, "reUnit": 20, "manual_number": "PER-008", "manual_link": "", "note": "Tính theo lần", "concurrentPerformers": 1, "allowedPositions": ["Ngành hàng", "Leader"],
          "timeWindows": [ { "startTime": "11:00", "endTime": "12:00" } ] },
        { "order": "9", "name": "Làm POP Peri", "typeTask": "Product", "frequency": "Weekly", "frequencyNumber": 2, "reUnit": 30, "manual_number": "PER-009", "manual_link": "", "note": "Tính theo lần", "concurrentPerformers": 2, "allowedPositions": ["Ngành hàng", "Leader"],
          "timeWindows": [ { "startTime": "14:30", "endTime": "14:45" } ] },
        { "order": "10", "name": "Giảm giá Peri", "typeTask": "Product", "frequency": "Daily", "frequencyNumber": 2, "reUnit": 1, "manual_number": "PER-010", "manual_link": "", "note": "Tính theo khối lượng rau củ (kg)", "concurrentPerformers": 2, "allowedPositions": ["Ngành hàng", "Leader"],
          "timeWindows": [ { "startTime": "20:00", "endTime": "20:15" } ] },
        { "order": "11", "name": "Kéo mặt Peri", "typeTask": "Product", "frequency": "Daily", "frequencyNumber": 1, "reUnit": 15, "manual_number": "PER-011", "manual_link": "", "note": "Tính theo lần", "concurrentPerformers": 2, "allowedPositions": ["Ngành hàng", "Leader"],
          "timeWindows": [ { "startTime": "09:00", "endTime": "09:25" }, { "startTime": "15:00", "endTime": "15:25" }, { "startTime": "20:00", "endTime": "20:25" } ] },
        { "order": "12", "name": "Lọc hàng Tươi sống", "typeTask": "Product", "frequency": "Daily", "frequencyNumber": 1, "reUnit": 15, "manual_number": "PER-012", "manual_link": "", "note": "Tính theo lần", "concurrentPerformers": 2, "allowedPositions": ["Ngành hàng", "Leader"],
          "timeWindows": [ { "startTime": "09:00", "endTime": "09:30" }, { "startTime": "15:00", "endTime": "15:30" }, { "startTime": "20:00", "endTime": "20:30" } ] }
      ]},
    { "id": "DRY", "order": 3, "code": "DRY", 
      "color": {
        "name": "blue", "bg": "#bfdbfe", "text": "#1e40af", "border": "#60a5fa", "hover": "#93c5fd",
        "tailwind_bg": "bg-blue-200", "tailwind_text": "text-blue-800", "tailwind_border": "border-blue-500"
      },
      "tasks": [
        { "order": "1", "name": "Lên hàng khô", "typeTask": "Product", "frequency": "Daily", "frequencyNumber": 1, "reUnit": 3, "manual_number": "DRY-001", "manual_link": "", "note": "Tính theo lượng hàng khô (kiện)", "concurrentPerformers": 0, "allowedPositions": ["Ngành hàng", "Leader"],
          "timeWindows": [ { "startTime": "14:00", "endTime": "17:00" } ] },
        { "order": "2", "name": "Kéo mặt hàng khô", "typeTask": "Product", "frequency": "Daily", "frequencyNumber": 2, "reUnit": 1.5, "manual_number": "DRY-002", "manual_link": "", "note": "Tính theo lượng hàng khô (kiện)", "concurrentPerformers": 0, "allowedPositions": ["Ngành hàng", "Leader"],
          "timeWindows": [ { "startTime": "12:30", "endTime": "13:00" }, { "startTime": "21:45", "endTime": "22:15" } ] },
        { "order": "3", "name": "Kiểm tra HSD hàng khô", "typeTask": "Product", "frequency": "Weekly", "frequencyNumber": 1, "reUnit": 60, "manual_number": "DRY-003", "manual_link": "", "note": "Tính theo lần", "concurrentPerformers": 2, "allowedPositions": ["Ngành hàng", "Leader"],
          "timeWindows": [ { "startTime": "15:00", "endTime": "16:15" } ] },
        { "order": "4", "name": "Bắn OOS", "typeTask": "Product", "frequency": "Daily", "frequencyNumber": 1, "reUnit": 30, "manual_number": "DRY-004", "manual_link": "", "note": "Tính theo lần", "concurrentPerformers": 1, "allowedPositions": ["Ngành hàng", "Leader"],
          "timeWindows": [ { "startTime": "10:00", "endTime": "10:30" } ] },
        { "order": "5", "name": "Kéo mặt COC", "typeTask": "Product", "frequency": "Daily", "frequencyNumber": 1, "reUnit": 20, "manual_number": "DRY-005", "manual_link": "", "note": "Tính theo lần", "concurrentPerformers": 2, "allowedPositions": ["Ngành hàng", "Leader"],
          "timeWindows": [ { "startTime": "09:00", "endTime": "09:05" }, { "startTime": "15:00", "endTime": "15:05" }, { "startTime": "20:00", "endTime": "20:05" } ] },
        { "order": "6", "name": "Làm PC/POP Dry", "typeTask": "Product", "frequency": "Weekly", "frequencyNumber": 3, "reUnit": 30, "manual_number": "DRY-006", "manual_link": "", "note": "Tính theo lần", "concurrentPerformers": 2, "allowedPositions": ["Ngành hàng", "Leader"],
          "timeWindows": [ { "startTime": "15:00", "endTime": "15:15" } ] },
        { "order": "7", "name": "Check tồn WH nóc kệ châm hàng", "typeTask": "Product", "frequency": "Daily", "frequencyNumber": 1, "reUnit": 1, "manual_number": "DRY-007", "manual_link": "", "note": "Tính theo lượng hàng khô (kiện)", "concurrentPerformers": 2, "allowedPositions": ["Ngành hàng", "Leader"],
          "timeWindows": [ { "startTime": "10:30", "endTime": "11:00" } ] },
        { "order": "8", "name": "Kéo mặt Grocery", "typeTask": "Product", "frequency": "Daily", "frequencyNumber": 1, "reUnit": 1, "manual_number": "DRY-008", "manual_link": "", "note": "Tính theo lượng hàng khô (kiện)", "concurrentPerformers": 0, "allowedPositions": ["Ngành hàng", "Leader"],
          "timeWindows": [ { "startTime": "12:30", "endTime": "13:00" }, { "startTime": "21:45", "endTime": "22:15" } ] },
        { "order": "9", "name": "Kéo mặt NF-HBC HL-SL", "typeTask": "Product", "frequency": "Daily", "frequencyNumber": 1, "reUnit": 1, "manual_number": "DRY-009", "manual_link": "", "note": "Tính theo lượng hàng khô (kiện)", "concurrentPerformers": 0, "allowedPositions": ["Ngành hàng", "Leader"],
          "timeWindows": [ { "startTime": "12:30", "endTime": "13:00" }, { "startTime": "21:45", "endTime": "22:15" } ] },
        { "order": "10", "name": "Key Auto ORD", "typeTask": "Product", "frequency": "Daily", "frequencyNumber": 1, "reUnit": 45, "manual_number": "DRY-010", "manual_link": "", "note": "Tính theo lần", "concurrentPerformers": 1, "allowedPositions": ["Ngành hàng", "Leader"],
          "timeWindows": [ { "startTime": "20:00", "endTime": "20:15" } ] },
        { "order": "11", "name": "Check Auto ORD", "typeTask": "Product", "frequency": "Daily", "frequencyNumber": 1, "reUnit": 30, "manual_number": "DRY-011", "manual_link": "", "note": "Tính theo lần", "concurrentPerformers": 1, "allowedPositions": ["Ngành hàng", "Leader"],
          "timeWindows": [ { "startTime": "20:15", "endTime": "20:30" } ] },
        { "order": "12", "name": "Thay POG", "typeTask": "Product", "frequency": "Monthly", "frequencyNumber": 2, "reUnit": 120, "manual_number": "DRY-012", "manual_link": "", "note": "Tính theo lần", "concurrentPerformers": 2, "allowedPositions": ["Ngành hàng", "Leader"],
          "timeWindows": [ { "startTime": "15:00", "endTime": "16:00" } ] },
        { "order": "13", "name": "Chuẩn bị kiểm kê năm", "typeTask": "Fixed", "frequency": "Yearly", "frequencyNumber": 1, "reUnit": 480, "manual_number": "DRY-013", "manual_link": "", "note": "Tính theo lần", "concurrentPerformers": 0, "allowedPositions": ["Ngành hàng", "Leader"],
          "timeWindows": [ { "startTime": "15:00", "endTime": "16:00" } ] }
      ]},
    { "id": "MMD", "order": 4, "code": "MMD", 
      "color": {
        "name": "amber", "bg": "#fde68a", "text": "#92400e", "border": "#facc15", "hover": "#fcd34d",
        "tailwind_bg": "bg-amber-200", "tailwind_text": "text-amber-800", "tailwind_border": "border-amber-500"
      },
      "tasks": [
        { "order": "1", "name": "Nhận hàng Peri", "typeTask": "Product", "frequency": "Daily", "frequencyNumber": 1, "reUnit": 60, "manual_number": "MMD-001", "manual_link": "", "note": "Tính theo lần", "concurrentPerformers": 2, "allowedPositions": ["MMD", "Leader"],
          "timeWindows": [ { "startTime": "06:00", "endTime": "11:00" } ] },
        { "order": "2", "name": "Nhận hàng Delica", "typeTask": "Product", "frequency": "Daily", "frequencyNumber": 1, "reUnit": 30, "manual_number": "MMD-002", "manual_link": "", "note": "Tính theo lần", "concurrentPerformers": 1, "allowedPositions": ["MMD", "Leader"],
          "timeWindows": [ { "startTime": "06:55", "endTime": "07:00" }, { "startTime": "10:00", "endTime": "10:05" } ] },
        { "order": "3", "name": "Nhận hàng RDC Dry", "typeTask": "Product", "frequency": "Daily", "frequencyNumber": 1, "reUnit": 90, "manual_number": "MMD-003", "manual_link": "", "note": "Tính theo lần", "concurrentPerformers": 2, "allowedPositions": ["MMD", "Leader"],
          "timeWindows": [ { "startTime": "11:00", "endTime": "15:00" } ] },
        { "order": "4", "name": "Nhận hàng RDC D&D", "typeTask": "Product", "frequency": "Daily", "frequencyNumber": 1, "reUnit": 45, "manual_number": "MMD-004", "manual_link": "", "note": "Tính theo lần", "concurrentPerformers": 2, "allowedPositions": ["MMD", "Leader"],
          "timeWindows": [ { "startTime": "09:30", "endTime": "09:45" } ] },
        { "order": "5", "name": "Nhận hàng D&D từ NCC", "typeTask": "Product", "frequency": "Daily", "frequencyNumber": 1, "reUnit": 45, "manual_number": "MMD-005", "manual_link": "", "note": "Tính theo lần", "concurrentPerformers": 2, "allowedPositions": ["MMD", "Leader"],
          "timeWindows": [ { "startTime": "07:00", "endTime": "08:00" } ] },
        { "order": "6", "name": "Làm báo cáo hóa đơn MMD", "typeTask": "Fixed", "frequency": "Daily", "frequencyNumber": 1, "reUnit": 30, "manual_number": "MMD-006", "manual_link": "", "note": "Tính theo lần", "concurrentPerformers": 1, "startTime": "", "endTime": "", "allowedPositions": ["MMD", "Leader"] },
        { "order": "7", "name": "Xử lý và update GTN/GRN", "typeTask": "Fixed", "frequency": "Daily", "frequencyNumber": 1, "reUnit": 60, "manual_number": "MMD-007", "manual_link": "", "note": "Tính theo lần", "concurrentPerformers": 1, "allowedPositions": ["MMD", "Leader"],
          "timeWindows": [ { "startTime": "13:00", "endTime": "13:10" } ] }
      ]},
    { "id": "LEADER", "order": 5, "code": "LEADER", 
      "color": {
        "name": "teal", "bg": "#99f6e4", "text": "#134e4a", "border": "#2dd4bf", "hover": "#5eead4",
        "tailwind_bg": "bg-teal-200", "tailwind_text": "text-teal-800", "tailwind_border": "border-teal-500"
      },
      "tasks": [
        { "order": "1", "name": "Mở kho", "typeTask": "Fixed", "frequency": "Daily", "frequencyNumber": 1, "reUnit": 15, "manual_number": "LEA-001", "manual_link": "", "note": "Tính theo lần", "concurrentPerformers": 1, "startTime": "05:30", "endTime": "05:37", "allowedPositions": ["Leader"], "shiftPlacement": { "type": "firstOfDay" } },
        { "order": "2", "name": "Đóng kho", "typeTask": "Fixed", "frequency": "Daily", "frequencyNumber": 1, "reUnit": 15, "manual_number": "LEA-002", "manual_link": "", "note": "Tính theo lần", "concurrentPerformers": 1, "startTime": "", "endTime": "", "allowedPositions": ["Leader"], "shiftPlacement": { "type": "lastOfDay" } },
        { "order": "3", "name": "Hủy hàng và update hệ thống", "typeTask": "Product", "frequency": "Daily", "frequencyNumber": 1, "reUnit": 30, "manual_number": "LEA-003", "manual_link": "", "note": "Tính theo lần", "concurrentPerformers": 1, "startTime": "13:55", "endTime": "22:15", "allowedPositions": ["Leader"] },
        { "order": "4", "name": "Đặt văn phòng phẩm", "typeTask": "Fixed", "frequency": "Weekly", "frequencyNumber": 1, "reUnit": 15, "manual_number": "LEA-004", "manual_link": "", "note": "Tính theo lần", "concurrentPerformers": 1, "startTime": "15:00", "endTime": "15:10", "allowedPositions": ["Leader"] },
        { "order": "5", "name": "Balancing", "typeTask": "Fixed", "frequency": "Daily", "frequencyNumber": 1, "reUnit": 20, "manual_number": "LEA-005", "manual_link": "", "note": "Tính theo lần", "concurrentPerformers": 1, 
          "timeWindows": [
            { "startTime": "13:30", "endTime": "13:40" },
            { "startTime": "21:00", "endTime": "21:10" }
          ],
          "allowedPositions": ["Leader"] 
        },
        { "order": "6", "name": "Kiểm tra HSD Tươi sống-Quản lý", "typeTask": "Product", "frequency": "Daily", "frequencyNumber": 1, "reUnit": 15, "manual_number": "LEA-006", "manual_link": "", "note": "Tính theo lần", "concurrentPerformers": 1, "startTime": "", "endTime": "", "allowedPositions": ["Leader"] },
        { "order": "7", "name": "Kiểm tra PC-POP", "typeTask": "Product", "frequency": "Daily", "frequencyNumber": 2, "reUnit": 15, "manual_number": "LEA-007", "manual_link": "", "note": "Tính theo lần", "concurrentPerformers": 1, "startTime": "", "endTime": "", "allowedPositions": ["Leader"] },
        { "order": "8", "name": "Kiểm tra hàng đổi trả", "typeTask": "Product", "frequency": "Daily", "frequencyNumber": 1, "reUnit": 15, "manual_number": "LEA-008", "manual_link": "", "note": "Tính theo lần", "concurrentPerformers": 1, "startTime": "", "endTime": "", "allowedPositions": ["Leader"] },
        { "order": "9", "name": "Tạo và chỉnh sửa DWS", "typeTask": "Fixed", "frequency": "Daily", "frequencyNumber": 1, "reUnit": 30, "manual_number": "LEA-009", "manual_link": "", "note": "Tính theo lần", "concurrentPerformers": 1, "startTime": "", "endTime": "", "allowedPositions": ["Leader"] },
        { "order": "10", "name": "Bàn giao tiền cho ngân hàng", "typeTask": "Fixed", "frequency": "Daily", "frequencyNumber": 1, "reUnit": 15, "manual_number": "LEA-010", "manual_link": "", "note": "Tính theo lần", "concurrentPerformers": 1, "startTime": "14:00", "endTime": "16:00", "allowedPositions": ["Leader"] },
        { "order": "11", "name": "Giảm giá Peri/Dry", "typeTask": "Product", "frequency": "Daily", "frequencyNumber": 1, "reUnit": 30, "manual_number": "LEA-011", "manual_link": "", "note": "Tính theo lần", "concurrentPerformers": 1, "startTime": "19:00", "endTime": "22:00", "allowedPositions": ["Leader"] },
        { "order": "12", "name": "Kiểm tra DWS", "typeTask": "Fixed", "frequency": "Daily", "frequencyNumber": 1, "reUnit": 15, "manual_number": "LEA-012", "manual_link": "", "note": "Tính theo lần", "concurrentPerformers": 1, "allowedPositions": ["Leader"], "shiftPlacement": { "type": "lastOfShift" } },
        { "order": "13", "name": "Xử lý công việc quản lý", "typeTask": "Fixed", "frequency": "Daily", "frequencyNumber": 1, "reUnit": 120, "manual_number": "LEA-013", "manual_link": "", "note": "Tính theo lần", "concurrentPerformers": 1, "startTime": "", "endTime": "", "allowedPositions": ["Leader"] }
      ]},
    { "id": "QC-FSH", "order": 6, "code": "QC-FSH", 
      "color": {
        "name": "purple", "bg": "#e9d5ff", "text": "#6b21a8", "border": "#c084fc", "hover": "#d8b4fe",
        "tailwind_bg": "bg-purple-200", "tailwind_text": "text-purple-800", "tailwind_border": "border-purple-500"
      },
      "tasks": [
        { "order": "1", "name": "5S khu vực POS", "typeTask": "Fixed", "frequency": "Daily", "frequencyNumber": 2, "reUnit": 15, "manual_number": "QCF-001", "manual_link": "", "note": "Tính theo lần", "concurrentPerformers": 1, "allowedPositions": ["POS", "Ngành hàng", "Aeon Cafe", "MMD", "Leader"],
          "timeWindows": [ { "startTime": "09:30", "endTime": "09:45" }, { "startTime": "22:00", "endTime": "22:15" } ] },
        { "order": "2", "name": "5S khu vực văn phòng", "typeTask": "Fixed", "frequency": "Daily", "frequencyNumber": 1, "reUnit": 15, "manual_number": "QCF-002", "manual_link": "", "note": "Tính theo lần", "concurrentPerformers": 1, "allowedPositions": ["Leader", "POS", "Ngành hàng", "Aeon Cafe", "MMD"],
          "timeWindows": [ { "startTime": "13:55", "endTime": "14:00" }, { "startTime": "22:20", "endTime": "22:25" } ] },
        { "order": "3", "name": "5S khu vực tươi sống", "typeTask": "Fixed", "frequency": "Daily", "frequencyNumber": 2, "reUnit": 20, "manual_number": "QCF-003", "manual_link": "", "note": "Tính theo lần", "concurrentPerformers": 2, "allowedPositions": ["Ngành hàng", "Leader"],
          "timeWindows": [ { "startTime": "13:00", "endTime": "13:10" }, { "startTime": "20:00", "endTime": "20:10" } ] },
        { "order": "4", "name": "5S khu vực MMD", "typeTask": "Fixed", "frequency": "Daily", "frequencyNumber": 1, "reUnit": 20, "manual_number": "QCF-004", "manual_link": "", "note": "Tính theo lần", "concurrentPerformers": 1, "allowedPositions": ["MMD", "Leader"],
          "timeWindows": [ { "startTime": "13:50", "endTime": "14:00" }, { "startTime": "21:50", "endTime": "22:00" } ] },
        { "order": "5", "name": "5S khu vực khách ngồi", "typeTask": "Fixed", "frequency": "Daily", "frequencyNumber": 3, "reUnit": 10, "manual_number": "QCF-005", "manual_link": "", "note": "Tính theo lần", "concurrentPerformers": 1, "allowedPositions": ["Aeon Cafe", "POS", "Ngành hàng", "Leader"],
          "timeWindows": [ { "startTime": "13:00", "endTime": "13:30" }, { "startTime": "21:00", "endTime": "21:30" } ] },
        { "order": "6", "name": "5S Kho hàng hóa", "typeTask": "Fixed", "frequency": "Daily", "frequencyNumber": 1, "reUnit": 30, "manual_number": "QCF-006", "manual_link": "", "note": "Tính theo lần", "concurrentPerformers": 2, "allowedPositions": ["MMD", "Ngành hàng", "Leader"],
          "timeWindows": [ { "startTime": "13:50", "endTime": "14:00" }, { "startTime": "21:50", "endTime": "22:00" } ] },
        { "order": "7", "name": "Tổng vệ sinh Chiller với ADV", "typeTask": "Fixed", "frequency": "Weekly", "frequencyNumber": 1, "reUnit": 60, "manual_number": "QCF-007", "manual_link": "", "note": "Tính theo lần", "concurrentPerformers": 2, "allowedPositions": ["Ngành hàng", "Leader"],
          "timeWindows": [] },
        { "order": "8", "name": "Cleaning Time 09:00", "typeTask": "Fixed", "frequency": "Daily", "frequencyNumber": 1, "reUnit": 15, "manual_number": "QCF-008", "manual_link": "", "note": "Tính theo lần", "concurrentPerformers": 0, "allowedPositions": ["Leader", "POS", "Ngành hàng", "Aeon Cafe", "MMD"],
          "timeWindows": [ { "startTime": "09:00", "endTime": "09:15" } ] },
        { "order": "9", "name": "Cleaning Time 15:00", "typeTask": "Fixed", "frequency": "Daily", "frequencyNumber": 1, "reUnit": 15, "manual_number": "QCF-009", "manual_link": "", "note": "Tính theo lần", "concurrentPerformers": 0, "allowedPositions": ["Leader", "POS", "Ngành hàng", "Aeon Cafe", "MMD"],
          "timeWindows": [ { "startTime": "15:00", "endTime": "15:15" } ] },
        { "order": "10", "name": "Cleaning Time 20:00", "typeTask": "Fixed", "frequency": "Daily", "frequencyNumber": 1, "reUnit": 15, "manual_number": "QCF-010", "manual_link": "", "note": "Tính theo lần", "concurrentPerformers": 0, "allowedPositions": ["Leader", "POS", "Ngành hàng", "Aeon Cafe", "MMD"],
          "timeWindows": [ { "startTime": "20:00", "endTime": "20:15" } ] },
        { "order": "11", "name": "Vệ sinh máy Trà Chanh, Milo", "typeTask": "Fixed", "frequency": "Daily", "frequencyNumber": 1, "reUnit": 15, "manual_number": "QCF-011", "manual_link": "", "note": "Tính theo lần", "concurrentPerformers": 1, "allowedPositions": ["Aeon Cafe", "Leader"],
          "timeWindows": [ { "startTime": "20:30", "endTime": "20:40" } ] },
        { "order": "12", "name": "Vệ sinh máy Cafe", "typeTask": "Fixed", "frequency": "Daily", "frequencyNumber": 1, "reUnit": 20, "manual_number": "QCF-012", "manual_link": "", "note": "Tính theo lần", "concurrentPerformers": 1, "allowedPositions": ["Aeon Cafe", "Leader"],
          "timeWindows": [] },
        { "order": "13", "name": "Check nhiệt độ", "typeTask": "Fixed", "frequency": "Daily", "frequencyNumber": 3, "reUnit": 10, "manual_number": "QCF-013", "manual_link": "", "note": "Tính theo lần", "concurrentPerformers": 1, "allowedPositions": ["Leader", "Ngành hàng"],
          "timeWindows": [ { "startTime": "09:00", "endTime": "09:05" }, { "startTime": "15:00", "endTime": "15:05" }, { "startTime": "20:00", "endTime": "20:05" } ] },
        { "order": "14", "name": "Vệ sinh bể tách mỡ", "typeTask": "Fixed", "frequency": "Weekly", "frequencyNumber": 1, "reUnit": 30, "manual_number": "QCF-014", "manual_link": "", "note": "Tính theo lần", "concurrentPerformers": 1, "allowedPositions": ["MMD", "Leader"],
          "timeWindows": [ { "startTime": "22:00", "endTime": "22:15" } ] },
        { "order": "15", "name": "5S Aeon Cafe", "typeTask": "Fixed", "frequency": "Daily", "frequencyNumber": 2, "reUnit": 15, "manual_number": "QCF-015", "manual_link": "", "note": "Tính theo lần", "concurrentPerformers": 1, "allowedPositions": ["Aeon Cafe", "Leader"],
          "timeWindows": [ { "startTime": "13:45", "endTime": "14:00" }, { "startTime": "21:15", "endTime": "22:00" } ] },
        { "order": "16", "name": "5S Khu vực bếp", "typeTask": "Fixed", "frequency": "Daily", "frequencyNumber": 2, "reUnit": 20, "manual_number": "QCF-016", "manual_link": "", "note": "Tính theo lần", "concurrentPerformers": 2, "allowedPositions": ["Aeon Cafe", "Leader"],
          "timeWindows": [ { "startTime": "22:00", "endTime": "22:20" } ] },
        { "order": "17", "name": "Vệ sinh tủ lạnh cuối ngày", "typeTask": "Fixed", "frequency": "Daily", "frequencyNumber": 1, "reUnit": 30, "manual_number": "QCF-017", "manual_link": "", "note": "Tính theo lần", "concurrentPerformers": 2, "allowedPositions": ["Ngành hàng", "Leader"],
          "timeWindows": [ { "startTime": "21:45", "endTime": "22:00" } ] },
        { "order": "18", "name": "Vệ sinh quầy kệ hàng khô", "typeTask": "Fixed", "frequency": "Weekly", "frequencyNumber": 1, "reUnit": 120, "manual_number": "QCF-018", "manual_link": "", "note": "Tính theo lần", "concurrentPerformers": 0, "allowedPositions": ["Ngành hàng", "Leader"],
          "timeWindows": [] },
        { "order": "19", "name": "Quét lau sàn", "typeTask": "Fixed", "frequency": "Daily", "frequencyNumber": 3, "reUnit": 20, "manual_number": "QCF-019", "manual_link": "", "note": "Tính theo lần", "concurrentPerformers": 2, "allowedPositions": ["POS", "Ngành hàng", "Aeon Cafe", "MMD", "Leader"],
          "timeWindows": [ { "startTime": "13:00", "endTime": "14:30" } ] }
      ]},
    { "id": "DELICA", "order": 7, "code": "DELICA", 
      "color": {
        "name": "indigo", "bg": "#c7d2fe", "text": "#3730a3", "border": "#818cf8", "hover": "#a5b4fc",
        "tailwind_bg": "bg-indigo-200", "tailwind_text": "text-indigo-800", "tailwind_border": "border-indigo-500"
      },
      "tasks": [
        { "order": "1", "name": "Pha chế Cafe", "typeTask": "CTM", "frequency": "Daily", "frequencyNumber": 1, "reUnit": 20, "manual_number": "DEL-001", "manual_link": "", "note": "Tính theo lần", "concurrentPerformers": 1, "allowedPositions": ["Aeon Cafe", "Leader"],
          "timeWindows": [] },
        { "order": "2", "name": "Chuẩn bị Aeon Cafe đầu ngày", "typeTask": "Product", "frequency": "Daily", "frequencyNumber": 1, "reUnit": 30, "manual_number": "DEL-002", "manual_link": "", "note": "Tính theo lần", "concurrentPerformers": 1, "allowedPositions": ["Aeon Cafe", "Leader"],
          "timeWindows": [ { "startTime": "06:00", "endTime": "06:15" } ] },
        { "order": "3", "name": "Lên hàng Delica", "typeTask": "Product", "frequency": "Daily", "frequencyNumber": 1, "reUnit": 15, "manual_number": "DEL-003", "manual_link": "", "note": "Tính theo lần", "concurrentPerformers": 1, "allowedPositions": ["Aeon Cafe", "Leader"],
          "timeWindows": [ { "startTime": "07:00", "endTime": "07:25" }, { "startTime": "10:00", "endTime": "10:25" } ] },
        { "order": "4", "name": "Kéo mặt Delica", "typeTask": "Product", "frequency": "Daily", "frequencyNumber": 1, "reUnit": 10, "manual_number": "DEL-004", "manual_link": "", "note": "Tính theo lần", "concurrentPerformers": 1, "allowedPositions": ["Aeon Cafe", "Leader"],
          "timeWindows": [ { "startTime": "10:00", "endTime": "10:10" }, { "startTime": "17:00", "endTime": "17:10" }, { "startTime": "20:00", "endTime": "20:10" } ] },
        { "order": "5", "name": "Kiểm tra HSD Delica", "typeTask": "Product", "frequency": "Daily", "frequencyNumber": 1, "reUnit": 10, "manual_number": "DEL-005", "manual_link": "", "note": "Tính theo lần", "concurrentPerformers": 1, "allowedPositions": ["Aeon Cafe", "Leader"],
          "timeWindows": [ { "startTime": "12:00", "endTime": "12:15" }, { "startTime": "20:10", "endTime": "20:25" } ] },
        { "order": "6", "name": "Giảm giá Delica", "typeTask": "Product", "frequency": "Daily", "frequencyNumber": 1, "reUnit": 5, "manual_number": "DEL-006", "manual_link": "", "note": "Tính theo lần", "concurrentPerformers": 1, "allowedPositions": ["Aeon Cafe", "Leader"],
          "timeWindows": [ { "startTime": "11:00", "endTime": "11:10" }, { "startTime": "17:00", "endTime": "17:10" } ] },
        { "order": "7", "name": "Kiểm tra POP Delica", "typeTask": "Product", "frequency": "Daily", "frequencyNumber": 1, "reUnit": 5, "manual_number": "DEL-007", "manual_link": "", "note": "Tính theo lần", "concurrentPerformers": 1, "allowedPositions": ["Aeon Cafe", "Leader"],
          "timeWindows": [ { "startTime": "10:10", "endTime": "10:20" } ] },
        { "order": "8", "name": "Đặt nguyên liệu Delica", "typeTask": "Product", "frequency": "Daily", "frequencyNumber": 1, "reUnit": 10, "manual_number": "DEL-008", "manual_link": "", "note": "Tính theo lần", "concurrentPerformers": 1, "allowedPositions": ["Aeon Cafe", "Leader"],
          "timeWindows": [ { "startTime": "10:00", "endTime": "10:05" } ] },
        { "order": "9", "name": "Đặt hàng Delica", "typeTask": "Product", "frequency": "Daily", "frequencyNumber": 1, "reUnit": 10, "manual_number": "DEL-009", "manual_link": "", "note": "Tính theo lần", "concurrentPerformers": 1, "allowedPositions": ["Aeon Cafe", "Leader"],
          "timeWindows": [ { "startTime": "11:00", "endTime": "11:15" } ] },
        { "order": "10", "name": "Chuẩn bị Aeon Cafe cho ngày hôm sau", "typeTask": "Product", "frequency": "Daily", "frequencyNumber": 1, "reUnit": 20, "manual_number": "DEL-010", "manual_link": "", "note": "Tính theo lần", "concurrentPerformers": 1, "allowedPositions": ["Aeon Cafe", "Leader"],
          "timeWindows": [ { "startTime": "15:30", "endTime": "15:40" } ] },
        { "order": "11", "name": "Bổ sung vật tư Aeon Cafe", "typeTask": "Product", "frequency": "Daily", "frequencyNumber": 1, "reUnit": 5, "manual_number": "DEL-011", "manual_link": "", "note": "Tính theo lần", "concurrentPerformers": 1, "allowedPositions": ["Aeon Cafe", "Leader"],
          "timeWindows": [ { "startTime": "06:15", "endTime": "06:30" }, { "startTime": "14:45", "endTime": "15:00" } ] },
        { "order": "12", "name": "Kiểm kê Delica", "typeTask": "Product", "frequency": "Monthly", "frequencyNumber": 1, "reUnit": 20, "manual_number": "DEL-012", "manual_link": "", "note": "Tính theo lần", "concurrentPerformers": 1, "allowedPositions": ["Aeon Cafe", "Leader"],
          "timeWindows": [ { "startTime": "15:00", "endTime": "17:00" } ] }
      ]},
    { "id": "DND", "order": 8, "code": "D&D", 
      "color": {
        "name": "red", "bg": "#fecaca", "text": "#991b1b", "border": "#f87171", "hover": "#fca5a5",
        "tailwind_bg": "bg-red-200", "tailwind_text": "text-red-800", "tailwind_border": "border-red-500"
      },
      "tasks": [
        { "order": "1", "name": "Lên hàng D&D", "typeTask": "Product", "frequency": "Daily", "frequencyNumber": 2, "reUnit": 30, "manual_number": "DND-001", "manual_link": "", "note": "Tính theo lần", "concurrentPerformers": 2, "allowedPositions": ["Ngành hàng", "Leader"],
          "timeWindows": [ { "startTime": "10:00", "endTime": "11:00" } ] },
        { "order": "2", "name": "Kéo mặt D&D", "typeTask": "Product", "frequency": "Daily", "frequencyNumber": 2, "reUnit": 15, "manual_number": "DND-002", "manual_link": "", "note": "Tính theo lần", "concurrentPerformers": 2, "allowedPositions": ["Ngành hàng", "Leader"],
          "timeWindows": [ { "startTime": "07:00", "endTime": "07:15" }, { "startTime": "15:00", "endTime": "15:15" }, { "startTime": "20:00", "endTime": "20:15" } ] },
        { "order": "3", "name": "Kiểm tra HSD D&D", "typeTask": "Product", "frequency": "Daily", "frequencyNumber": 2, "reUnit": 15, "manual_number": "DND-003", "manual_link": "", "note": "Tính theo lần", "concurrentPerformers": 1, "allowedPositions": ["Ngành hàng", "Leader"],
          "timeWindows": [ { "startTime": "20:00", "endTime": "21:00" } ] },
        { "order": "4", "name": "Đặt hàng D&D", "typeTask": "Product", "frequency": "Daily", "frequencyNumber": 1, "reUnit": 20, "manual_number": "DND-004", "manual_link": "", "note": "Tính theo lần", "concurrentPerformers": 1, "allowedPositions": ["Ngành hàng", "Leader"],
          "timeWindows": [ { "startTime": "10:00", "endTime": "11:00" } ] },
        { "order": "5", "name": "Làm PC/POP D&D", "typeTask": "Product", "frequency": "Weekly", "frequencyNumber": 1, "reUnit": 30, "manual_number": "DND-005", "manual_link": "", "note": "Tính theo lần", "concurrentPerformers": 1, "allowedPositions": ["Ngành hàng", "Leader"],
          "timeWindows": [ { "startTime": "15:00", "endTime": "15:15" } ] }
      ]},
    { "id": "OTHER", "order": 9, "code": "OTHER", 
      "color": {
        "name": "pink", "bg": "#fbcfe8", "text": "#9d174d", "border": "#f472b6", "hover": "#f9a8d4",
        "tailwind_bg": "bg-pink-200", "tailwind_text": "text-pink-800", "tailwind_border": "border-pink-500"
      },
      "tasks": [
        { "order": "1", "name": "Đổi PC", "typeTask": "Product", "frequency": "Weekly", "frequencyNumber": 1, "reUnit": 60, "manual_number": "OTH-001", "manual_link": "", "note": "Tính theo lần", "concurrentPerformers": 2, "allowedPositions": ["Ngành hàng", "Leader"],
          "timeWindows": [ { "startTime": "21:50", "endTime": "22:30" } ] },
        { "order": "2", "name": "Đổi POP", "typeTask": "Product", "frequency": "Weekly", "frequencyNumber": 1, "reUnit": 60, "manual_number": "OTH-002", "manual_link": "", "note": "Tính theo lần", "concurrentPerformers": 2, "allowedPositions": ["Ngành hàng", "Leader"],
          "timeWindows": [ { "startTime": "07:00", "endTime": "08:00" } ] },
        { "order": "3", "name": "BRF Đầu ca", "typeTask": "Fixed", "frequency": "Daily", "frequencyNumber": 1, "reUnit": 15, "manual_number": "OTH-003", "manual_link": "", "note": "Tính theo lần", "concurrentPerformers": 0, "allowedPositions": ["Leader", "POS", "Ngành hàng", "Aeon Cafe", "MMD"], "shiftPlacement": { "type": "firstOfShift" },
          "timeWindows": [] },
        { "order": "4", "name": "Kiểm kê tháng Leader", "typeTask": "Product", "frequency": "Monthly", "frequencyNumber": 1, "reUnit": 240, "manual_number": "OTH-004", "manual_link": "", "note": "Tính theo lần", "concurrentPerformers": 1, "allowedPositions": ["Leader"],
          "timeWindows": [ { "startTime": "19:00", "endTime": "22:00" } ] },
        { "order": "5", "name": "Kiểm kê tháng Staff", "typeTask": "Product", "frequency": "Monthly", "frequencyNumber": 1, "reUnit": 180, "manual_number": "OTH-005", "manual_link": "", "note": "Tính theo lần", "concurrentPerformers": 0, "allowedPositions": ["POS", "Ngành hàng", "Aeon Cafe", "MMD"],
          "timeWindows": [ { "startTime": "19:00", "endTime": "22:00" } ] },
        { "order": "6", "name": "Kiểm kê năm", "typeTask": "Product", "frequency": "Yearly", "frequencyNumber": 1, "reUnit": 480, "manual_number": "OTH-006", "manual_link": "", "note": "Tính theo lần", "concurrentPerformers": 0, "startTime": "", "endTime": "", "allowedPositions": ["Leader", "POS", "Ngành hàng", "Aeon Cafe", "MMD"] },
        { "order": "7", "name": "Tạo GE cho focus Item", "typeTask": "Product", "frequency": "Weekly", "frequencyNumber": 1, "reUnit": 30, "manual_number": "OTH-007", "manual_link": "", "note": "Tính theo lần", "concurrentPerformers": 2, "allowedPositions": ["Ngành hàng", "Leader"],
          "timeWindows": [] },
        { "order": "8", "name": "Chuẩn bị Tasting", "typeTask": "CTM", "frequency": "Daily", "frequencyNumber": 1, "reUnit": 30, "manual_number": "OTH-008", "manual_link": "", "note": "Tính theo lần", "concurrentPerformers": 1, "startTime": "", "endTime": "", "allowedPositions": ["Ngành hàng", "Aeon Cafe", "Leader"] },
        { "order": "9", "name": "Chuẩn bị tem phụ", "typeTask": "Product", "frequency": "Daily", "frequencyNumber": 1, "reUnit": 30, "manual_number": "OTH-009", "manual_link": "", "note": "Tính theo lần", "concurrentPerformers": 2, "allowedPositions": ["MMD", "Ngành hàng", "Leader"],
          "timeWindows": [ { "startTime": "20:30", "endTime": "21:00" } ] },
        { "order": "10", "name": "Break Time", "typeTask": "Fixed", "frequency": "Daily", "frequencyNumber": 1, "reUnit": 60, "manual_number": "OTH-010", "manual_link": "", "note": "Tính theo lần", "concurrentPerformers": 0, "allowedPositions": ["Leader", "POS", "Ngành hàng", "Aeon Cafe", "MMD"],
          "timeWindows": [ { "startTime": "10:00", "endTime": "12:00" }, { "startTime": "16:00", "endTime": "19:00" } ] },
        { "order": "11", "name": "Kiểm tra DWS", "typeTask": "Fixed", "frequency": "Daily", "frequencyNumber": 1, "reUnit": 15, "manual_number": "OTH-011", "manual_link": "", "note": "Tính theo lần", "concurrentPerformers": 1, "allowedPositions": ["Leader"],
          "timeWindows": [ { "startTime": "06:00", "endTime": "06:05" }, { "startTime": "13:55", "endTime": "14:00" }, { "startTime": "14:25", "endTime": "14:30" }, { "startTime": "22:25", "endTime": "22:30" } ] },
        { "order": "12", "name": "Sampling", "typeTask": "CTM", "frequency": "Daily", "frequencyNumber": 1, "reUnit": 60, "manual_number": "OTH-012", "manual_link": "", "note": "Tính theo lần", "concurrentPerformers": 1, "startTime": "", "endTime": "", "allowedPositions": ["Ngành hàng", "Aeon Cafe", "Leader"] },
        { "order": "13", "name": "Trưng POP Member Day", "typeTask": "Product", "frequency": "Monthly", "frequencyNumber": 1, "reUnit": 60, "manual_number": "OTH-013", "manual_link": "", "note": "Tính theo lần", "concurrentPerformers": 2, "allowedPositions": ["Ngành hàng", "Leader"],
          "timeWindows": [ { "startTime": "21:45", "endTime": "22:00" } ] },
        { "order": "14", "name": "Thu POP Member Day", "typeTask": "Product", "frequency": "Monthly", "frequencyNumber": 1, "reUnit": 30, "manual_number": "OTH-014", "manual_link": "", "note": "Tính theo lần", "concurrentPerformers": 2, "allowedPositions": ["Ngành hàng", "Leader"],
          "timeWindows": [ { "startTime": "21:45", "endTime": "22:00" } ] },
        { "order": "15", "name": "Giao hàng", "typeTask": "CTM", "frequency": "Daily", "frequencyNumber": 1, "reUnit": 120, "manual_number": "OTH-015", "manual_link": "", "note": "Tính theo lần", "concurrentPerformers": 1, "allowedPositions": ["MMD", "Leader"],
          "timeWindows": [ { "startTime": "09:00", "endTime": "11:00" }, { "startTime": "14:00", "endTime": "16:30" } ] },
        { "order": "16", "name": "Họp hành Đào tạo Kiểm tra", "typeTask": "Fixed", "frequency": "Daily", "frequencyNumber": 1, "reUnit": 60, "manual_number": "OTH-016", "manual_link": "", "note": "Tính theo lần", "concurrentPerformers": 0, "startTime": "", "endTime": "", "allowedPositions": ["Leader", "POS", "Ngành hàng", "Aeon Cafe", "MMD"] }
      ]
    }
  ]
}